ethbinductor/__init__.py
ethbinductor/__main__.py
ethbinductor/bind.py
ethbinductor/cli.py
ethbinductor/conductor.py
ethbinductor/conf.py
ethbinductor/providers/__init__.py
ethbinductor/providers/abi/__init__.py
ethbinductor/providers/abi/etherscan.py
ethbinductor/providers/abi/file.py
ethbinductor/providers/abi/http_base.py
ethbinductor/providers/output/__init__.py
ethbinductor/providers/output/file.py
ethbinductor/providers/output/output_base.py
ethbinductor/providers/output/py_print.py
ethbinductor/samples/BindBase.py
ethbinductor/utils.py
ethbinductor-0.0.9.dist-info/LICENSE
ethbinductor-0.0.9.dist-info/METADATA
ethbinductor-0.0.9.dist-info/WHEEL
ethbinductor-0.0.9.dist-info/entry_points.txt
ethbinductor-0.0.9.dist-info/RECORD
